hwp_hwpx_parser/__init__.py
hwp_hwpx_parser/hwp5.py
hwp_hwpx_parser/hwpx.py
hwp_hwpx_parser/models.py
hwp_hwpx_parser/reader.py
hwp_hwpx_parser-0.1.4.dist-info/licenses/LICENSE
hwp_hwpx_parser-0.1.4.dist-info/METADATA
hwp_hwpx_parser-0.1.4.dist-info/WHEEL
hwp_hwpx_parser-0.1.4.dist-info/top_level.txt
hwp_hwpx_parser-0.1.4.dist-info/RECORD
