Metadata-Version: 2.4
Name: hwp-hwpx-parser
Version: 0.1.4
Summary: 순수 Python HWP/HWPX 파서 - JVM 없이 텍스트, 표, 각주, 메모 추출
Author-email: Daehyeon Kim <qwertypotter@gachon.ac.kr>
License-Expression: Apache-2.0
Project-URL: Homepage, https://github.com/KimDaehyeon6873/hwp-hwpx-parser
Project-URL: Repository, https://github.com/KimDaehyeon6873/hwp-hwpx-parser.git
Project-URL: Bug Tracker, https://github.com/KimDaehyeon6873/hwp-hwpx-parser/issues
Keywords: hwp,hwpx,korean,word-processor,parser,text-extraction
Classifier: Development Status :: 3 - Alpha
Classifier: Intended Audience :: Developers
Classifier: Operating System :: OS Independent
Classifier: Programming Language :: Python :: 3
Classifier: Programming Language :: Python :: 3.8
Classifier: Programming Language :: Python :: 3.9
Classifier: Programming Language :: Python :: 3.10
Classifier: Programming Language :: Python :: 3.11
Classifier: Programming Language :: Python :: 3.12
Classifier: Programming Language :: Python :: 3.13
Classifier: Programming Language :: Python :: 3.14
Classifier: Topic :: Text Processing :: Markup
Requires-Python: >=3.8
License-File: LICENSE
Requires-Dist: olefile>=0.46
Provides-Extra: dev
Requires-Dist: pytest>=7.0; extra == "dev"
Requires-Dist: pytest-cov>=4.0; extra == "dev"
Requires-Dist: black>=22.0; extra == "dev"
Requires-Dist: isort>=5.0; extra == "dev"
Requires-Dist: flake8>=4.0; extra == "dev"
Requires-Dist: mypy>=1.0; extra == "dev"
Provides-Extra: docs
Requires-Dist: sphinx>=5.0; extra == "docs"
Requires-Dist: sphinx-rtd-theme>=1.2; extra == "docs"
Provides-Extra: build
Requires-Dist: build>=0.10.0; extra == "build"
Requires-Dist: twine>=4.0.0; extra == "build"
Dynamic: license-file
